resolvr/__init__.py
resolvr/main.py
resolvr-1.0.dist-info/LICENSE
resolvr-1.0.dist-info/METADATA
resolvr-1.0.dist-info/WHEEL
resolvr-1.0.dist-info/entry_points.txt
resolvr-1.0.dist-info/top_level.txt
resolvr-1.0.dist-info/RECORD
