Metadata-Version: 2.1
Name: resolvr
Version: 1.0
Summary: A penetration testing tool to resolve domains and optionally filter on in-scope results.
Home-page: https://gitlab.com/TheTwitchy/resolvr
Author: TheTwitchy
Author-email: thetwitchy@thetwitchy.com
License: MIT
Platform: UNKNOWN
Classifier: Programming Language :: Python :: 3
Classifier: License :: OSI Approved :: MIT License
Classifier: Operating System :: OS Independent
Classifier: Topic :: Security
Requires-Python: >=3.6
Requires-Dist: netaddr
Requires-Dist: requests
Requires-Dist: termcolor
